{
  "version": "1.0",
  "chainId": "42161",
  "createdAt": 1780500000,
  "meta": {
    "name": "Magneta wave \u2014 accept ownership (arbitrum)",
    "description": "Second leg of Ownable2Step: Safe 0x4AeA3A398Db41b45e146c08131aD27c75b02EC2F accepts ownership of 11 redeploy-wave contracts on arbitrum. Run AFTER deployer executes transferOwnership.ts --network arbitrum. 1-step (no accept needed): MagnetaBridgeOApp."
  },
  "transactions": [
    {
      "to": "0x822AbCc5BC4012f54dcc36034De3B70BfdA12d43",
      "value": "0",
      "data": "0x79ba5097",
      "contractMethod": null,
      "contractInputsValues": null
    },
    {
      "to": "0x437912A1Eb375d51061e9Dcd6d9a1B465c5072aE",
      "value": "0",
      "data": "0x79ba5097",
      "contractMethod": null,
      "contractInputsValues": null
    },
    {
      "to": "0xCeBf85B5AD944A4531d942579da85DFd8f37b425",
      "value": "0",
      "data": "0x79ba5097",
      "contractMethod": null,
      "contractInputsValues": null
    },
    {
      "to": "0xC59c1A1ff4F9a7129D5AE29b8636e35C8B603547",
      "value": "0",
      "data": "0x79ba5097",
      "contractMethod": null,
      "contractInputsValues": null
    },
    {
      "to": "0x6F5D88382123161f69e9F08f569515bf79AB8253",
      "value": "0",
      "data": "0x79ba5097",
      "contractMethod": null,
      "contractInputsValues": null
    },
    {
      "to": "0xa8fb7b4e5CFC55A06Ae7551060e66e353f60A984",
      "value": "0",
      "data": "0x79ba5097",
      "contractMethod": null,
      "contractInputsValues": null
    },
    {
      "to": "0xd747Dd890749584052725791aE994572f6027059",
      "value": "0",
      "data": "0x79ba5097",
      "contractMethod": null,
      "contractInputsValues": null
    },
    {
      "to": "0xD56530A88447F2955106371e74A6fD85Ab03b5f6",
      "value": "0",
      "data": "0x79ba5097",
      "contractMethod": null,
      "contractInputsValues": null
    },
    {
      "to": "0x29e7884d0D73Bed10FEF50F1E293c91221c9b28F",
      "value": "0",
      "data": "0x79ba5097",
      "contractMethod": null,
      "contractInputsValues": null
    },
    {
      "to": "0x05b853e7F18b64a73d3aAd8203292C71c62ceBe9",
      "value": "0",
      "data": "0x79ba5097",
      "contractMethod": null,
      "contractInputsValues": null
    },
    {
      "to": "0xB95032B64A6B8D2217DE2076351CbFA10F2B058E",
      "value": "0",
      "data": "0x79ba5097",
      "contractMethod": null,
      "contractInputsValues": null
    }
  ]
}
